rtl/data_memory.v
module data_memory (
    input clk,
    /* verilator lint_off UNUSEDSIGNAL */
    input [31:0] addr,
    /* verilator lint_off UNUSEDSIGNAL */
    input [31:0] write_data,
    input mem_read,
    input mem_write,
    output reg [31:0] read_data
);
    reg [31:0] memory [0:255]; // 1KB memory
    
    always @(posedge clk) begin
        if (mem_write) begin
            memory[addr[9:2]] <= write_data;
        end
    end
    
    always @(*) begin
        if (mem_read) begin
            read_data = memory[addr[9:2]];
        end else begin
            read_data = 32'd0;
        end
    end
    integer i;
    initial begin
        // Initialize memory
        for (i = 0; i < 256; i = i + 1) begin
            memory[i] = 32'd0;
        end
    end
endmodule

rtl/alu.v
module alu (
    input [31:0] a, b,
    input [3:0] alu_control,
    output reg [31:0] result,
    output zero
);
    always @(*) begin
        case (alu_control)
            4'b0000: result = a & b;    // AND
            4'b0001: result = a | b;    // OR
            4'b0010: result = a + b;    // ADD
            4'b1000: result = a ^ b;    // XOR
            4'b0110: result = a - b;    // SUB
            4'b0111: result = (a < b) ? 32'd1 : 32'd0; // SLT
            // 4'b1100: result = ~(a | b); // NOR
            default: result = 32'd0;
        endcase
    end
    
    assign zero = (result == 32'd0);
endmodule

rtl/sign_extend.v
module sign_extend (
    /* verilator lint_off UNUSEDSIGNAL */
    input [31:0] instruction,
    /* verilator lint_off UNUSEDSIGNAL */
    input [1:0] imm_src,
    output reg [31:0] imm_ext
);
    always @(*) begin
        case (imm_src)
            2'b00: imm_ext = {{20{instruction[31]}}, instruction[31:20]}; // I-type
            2'b01: imm_ext = {{20{instruction[31]}}, instruction[31:25], instruction[11:7]}; // S-type
            2'b10: imm_ext = {{20{instruction[31]}}, instruction[7], instruction[30:25], instruction[11:8], 1'b0}; // B-type
            default: imm_ext = 32'd0;
        endcase
    end
endmodule

rtl/register_file.v
module register_file (
    input clk,
    input reset,
    input reg_write,
    input [4:0] read_reg1,
    input [4:0] read_reg2,
    input [4:0] write_reg,
    input [31:0] write_data,
    output [31:0] read_data1,
    output [31:0] read_data2
);
    reg [31:0] registers [0:31];
    
    assign read_data1 = (read_reg1 != 0) ? registers[read_reg1] : 32'd0;
    assign read_data2 = (read_reg2 != 0) ? registers[read_reg2] : 32'd0;
    integer i;
    always @(posedge clk or posedge reset) begin
        if (reset) begin
            for (i = 0; i < 32; i = i + 1) begin
                registers[i] <= 32'd0;
            end
        end else if (reg_write && write_reg != 0) begin
            registers[write_reg] <= write_data;
        end
    end
endmodule

rtl/control_unit.v
module control_unit (
    input [6:0] opcode,
    output reg reg_write,
    output reg alu_src,
    output reg mem_to_reg,
    output reg mem_read,
    output reg mem_write,
    output reg branch,
    output reg [1:0] alu_op,
    output reg [1:0] imm_src
);
    always @(*) begin
        case (opcode)
            7'b0110011: begin // R-type
                reg_write = 1'b1;
                alu_src = 1'b0;
                mem_to_reg = 1'b0;
                mem_read = 1'b0;
                mem_write = 1'b0;
                branch = 1'b0;
                alu_op = 2'b10;
                imm_src = 2'b00;
            end
            7'b0000011: begin // lw
                reg_write = 1'b1;
                alu_src = 1'b1;
                mem_to_reg = 1'b1;
                mem_read = 1'b1;
                mem_write = 1'b0;
                branch = 1'b0;
                alu_op = 2'b00;
                imm_src = 2'b00;
            end
            7'b0100011: begin // sw
                reg_write = 1'b0;
                alu_src = 1'b1;
                mem_to_reg = 1'b0;
                mem_read = 1'b0;
                mem_write = 1'b1;
                branch = 1'b0;
                alu_op = 2'b00;
                imm_src = 2'b01;
            end
            7'b1100011: begin // beq
                reg_write = 1'b0;
                alu_src = 1'b0;
                mem_to_reg = 1'b0;
                mem_read = 1'b0;
                mem_write = 1'b0;
                branch = 1'b1;
                alu_op = 2'b01;
                imm_src = 2'b10;
            end
            7'b0010011: begin // I-type (addi, etc.)
                reg_write = 1'b1;
                alu_src = 1'b1;
                mem_to_reg = 1'b0;
                mem_read = 1'b0;
                mem_write = 1'b0;
                branch = 1'b0;
                alu_op = 2'b00;
                imm_src = 2'b00;
            end
            default: begin
                reg_write = 1'b0;
                alu_src = 1'b0;
                mem_to_reg = 1'b0;
                mem_read = 1'b0;
                mem_write = 1'b0;
                branch = 1'b0;
                alu_op = 2'b00;
                imm_src = 2'b00;
            end
        endcase
    end
endmodule

rtl/instruction_memory.v
module instruction_memory (
    /* verilator lint_off UNUSEDSIGNAL */
    input [31:0] pc,
    /* verilator lint_off UNUSEDSIGNAL */
    output [31:0] instruction
);
    reg [31:0] memory [0:255]; // 1KB memory
    
    assign instruction = memory[pc[9:2]]; // Word aligned
    
    initial begin
        $readmemh("test2.hex", memory); // Load instructions from hex file
    end
endmodule

rtl/pc.v
module pc (
    input clk,
    input reset,
    input [31:0] next_pc,
    output reg [31:0] current_pc
);
    always @(posedge clk or posedge reset) begin
        if (reset) begin
            current_pc <= 32'd0;
        end else begin
            current_pc <= next_pc;
        end
    end
endmodule

rtl/riscv_top.v
module riscv_top (
    input clk,
    input reset
);
    // PC signals
    wire [31:0] pc;
    wire [31:0] next_pc;
    
    // Instruction memory signals
    wire [31:0] instruction;
    
    // Control unit signals
    wire reg_write;
    wire alu_src;
    wire mem_to_reg;
    wire mem_read;
    wire mem_write;
    wire branch;
    wire [1:0] alu_op;
    wire [1:0] imm_src;
    
    // Register file signals
    wire [31:0] read_data1;
    wire [31:0] read_data2;
    wire [31:0] write_data;
    
    // ALU signals
    wire [31:0] alu_result;
    wire alu_zero;
    wire [3:0] alu_control;
    
    // Sign extend signals
    wire [31:0] imm_ext;
    
    // Data memory signals
    wire [31:0] mem_read_data;
    
    // Internal signals
    wire [31:0] alu_src_b;
    wire pc_src;
    wire [31:0] pc_plus_4;
    wire [31:0] pc_branch;
    
    // Instantiate PC
    pc pc_inst (
        .clk(clk),
        .reset(reset),
        .next_pc(next_pc),
        .current_pc(pc)
    );
    
    // PC + 4
    assign pc_plus_4 = pc + 32'd4;
    
    // PC branch target
    assign pc_branch = pc + imm_ext;
    
    // PC source mux
    assign pc_src = branch & alu_zero;
    assign next_pc = pc_src ? pc_branch : pc_plus_4;
    
    // Instruction memory
    instruction_memory imem (
        .pc(pc),
        .instruction(instruction)
    );
    
    // Control unit
    control_unit control (
        .opcode(instruction[6:0]),
        .reg_write(reg_write),
        .alu_src(alu_src),
        .mem_to_reg(mem_to_reg),
        .mem_read(mem_read),
        .mem_write(mem_write),
        .branch(branch),
        .alu_op(alu_op),
        .imm_src(imm_src)
    );
    
    // Register file
    register_file reg_file (
        .clk(clk),
        .reset(reset),
        .reg_write(reg_write),
        .read_reg1(instruction[19:15]),
        .read_reg2(instruction[24:20]),
        .write_reg(instruction[11:7]),
        .write_data(write_data),
        .read_data1(read_data1),
        .read_data2(read_data2)
    );
    
    // Sign extend
    sign_extend sign_ext (
        .instruction(instruction),
        .imm_src(imm_src),
        .imm_ext(imm_ext)
    );
    
    // ALU source mux
    assign alu_src_b = alu_src ? imm_ext : read_data2;
    
    // ALU control
    // assign alu_control[3] = alu_op[0] | (alu_op[1] & instruction[30]);
    // assign alu_control[2] = ~alu_op[1] | ~instruction[14];
    // assign alu_control[1] = alu_op[1] & (instruction[13] | instruction[14]);
    // assign alu_control[0] = alu_op[1] & (instruction[12] | instruction[13]);
    // 新控制信号生成逻辑（更清晰的优先级）
    assign alu_control = 
    (alu_op == 2'b00) ? 4'b0010 :               // I-type (addi/lw/sw): ADD
    (alu_op == 2'b01) ? 4'b0110 :               // Branch: SUB
    // R-type指令
    (instruction[14:12] == 3'b000) ? 
        (instruction[30] ? 4'b0110 : 4'b0010) : // ADD/SUB
    (instruction[14:12] == 3'b111) ? 4'b0000 :  // AND
    (instruction[14:12] == 3'b110) ? 4'b0001 :  // OR
    (instruction[14:12] == 3'b100) ? 4'b1000 :  // XOR
    (instruction[14:12] == 3'b010) ? 4'b0111 :  // SLT
    (instruction[14:12] == 3'b001) ? 4'b1001 :  // SLL
    (instruction[14:12] == 3'b101) ? 
        (instruction[30] ? 4'b1011 : 4'b1010) : // SRL/SRA
    4'b0000;                                    // Default
    
    // ALU
    alu alu_inst (
        .a(read_data1),
        .b(alu_src_b),
        .alu_control(alu_control),
        .result(alu_result),
        .zero(alu_zero)
    );
    
    // Data memory
    data_memory dmem (
        .clk(clk),
        .addr(alu_result),
        .write_data(read_data2),
        .mem_read(mem_read),
        .mem_write(mem_write),
        .read_data(mem_read_data)
    );
    
    // Write back mux
    assign write_data = mem_to_reg ? mem_read_data : alu_result;
endmodule

riscv_sim.vcd
$version Generated by VerilatedVcd $end
$timescale 1ps $end

 $scope module TOP $end
  $var wire  1 ^ clk $end
  $var wire  1 _ reset $end
  $scope module riscv_top $end
   $var wire  4 3 alu_control [3:0] $end
   $var wire  2 - alu_op [1:0] $end
   $var wire 32 1 alu_result [31:0] $end
   $var wire  1 ( alu_src $end
   $var wire 32 5 alu_src_b [31:0] $end
   $var wire  1 2 alu_zero $end
   $var wire  1 , branch $end
   $var wire  1 ^ clk $end
   $var wire 32 4 imm_ext [31:0] $end
   $var wire  2 . imm_src [1:0] $end
   $var wire 32 & instruction [31:0] $end
   $var wire  1 * mem_read $end
   $var wire 32 a mem_read_data [31:0] $end
   $var wire  1 ) mem_to_reg $end
   $var wire  1 + mem_write $end
   $var wire 32 % next_pc [31:0] $end
   $var wire 32 $ pc [31:0] $end
   $var wire 32 8 pc_branch [31:0] $end
   $var wire 32 7 pc_plus_4 [31:0] $end
   $var wire  1 6 pc_src $end
   $var wire 32 / read_data1 [31:0] $end
   $var wire 32 0 read_data2 [31:0] $end
   $var wire  1 ' reg_write $end
   $var wire  1 _ reset $end
   $var wire 32 ` write_data [31:0] $end
   $scope module alu_inst $end
    $var wire 32 / a [31:0] $end
    $var wire  4 3 alu_control [3:0] $end
    $var wire 32 5 b [31:0] $end
    $var wire 32 1 result [31:0] $end
    $var wire  1 2 zero $end
   $upscope $end
   $scope module control $end
    $var wire  2 - alu_op [1:0] $end
    $var wire  1 ( alu_src $end
    $var wire  1 , branch $end
    $var wire  2 . imm_src [1:0] $end
    $var wire  1 * mem_read $end
    $var wire  1 ) mem_to_reg $end
    $var wire  1 + mem_write $end
    $var wire  7 9 opcode [6:0] $end
    $var wire  1 ' reg_write $end
   $upscope $end
   $scope module dmem $end
    $var wire 32 1 addr [31:0] $end
    $var wire  1 ^ clk $end
    $var wire  1 * mem_read $end
    $var wire  1 + mem_write $end
    $var wire 32 a read_data [31:0] $end
    $var wire 32 0 write_data [31:0] $end
    $scope module unnamedblk1 $end
     $var wire 32 # i [31:0] $end
    $upscope $end
   $upscope $end
   $scope module imem $end
    $var wire 32 & instruction [31:0] $end
    $var wire 32 $ pc [31:0] $end
   $upscope $end
   $scope module pc_inst $end
    $var wire  1 ^ clk $end
    $var wire 32 $ current_pc [31:0] $end
    $var wire 32 % next_pc [31:0] $end
    $var wire  1 _ reset $end
   $upscope $end
   $scope module reg_file $end
    $var wire  1 ^ clk $end
    $var wire 32 / read_data1 [31:0] $end
    $var wire 32 0 read_data2 [31:0] $end
    $var wire  5 : read_reg1 [4:0] $end
    $var wire  5 ; read_reg2 [4:0] $end
    $var wire  1 ' reg_write $end
    $var wire 32 = registers[0] [31:0] $end
    $var wire 32 G registers[10] [31:0] $end
    $var wire 32 H registers[11] [31:0] $end
    $var wire 32 I registers[12] [31:0] $end
    $var wire 32 J registers[13] [31:0] $end
    $var wire 32 K registers[14] [31:0] $end
    $var wire 32 L registers[15] [31:0] $end
    $var wire 32 M registers[16] [31:0] $end
    $var wire 32 N registers[17] [31:0] $end
    $var wire 32 O registers[18] [31:0] $end
    $var wire 32 P registers[19] [31:0] $end
    $var wire 32 > registers[1] [31:0] $end
    $var wire 32 Q registers[20] [31:0] $end
    $var wire 32 R registers[21] [31:0] $end
    $var wire 32 S registers[22] [31:0] $end
    $var wire 32 T registers[23] [31:0] $end
    $var wire 32 U registers[24] [31:0] $end
    $var wire 32 V registers[25] [31:0] $end
    $var wire 32 W registers[26] [31:0] $end
    $var wire 32 X registers[27] [31:0] $end
    $var wire 32 Y registers[28] [31:0] $end
    $var wire 32 Z registers[29] [31:0] $end
    $var wire 32 ? registers[2] [31:0] $end
    $var wire 32 [ registers[30] [31:0] $end
    $var wire 32 \ registers[31] [31:0] $end
    $var wire 32 @ registers[3] [31:0] $end
    $var wire 32 A registers[4] [31:0] $end
    $var wire 32 B registers[5] [31:0] $end
    $var wire 32 C registers[6] [31:0] $end
    $var wire 32 D registers[7] [31:0] $end
    $var wire 32 E registers[8] [31:0] $end
    $var wire 32 F registers[9] [31:0] $end
    $var wire  1 _ reset $end
    $var wire 32 ` write_data [31:0] $end
    $var wire  5 < write_reg [4:0] $end
    $scope module unnamedblk1 $end
     $var wire 32 ] i [31:0] $end
    $upscope $end
   $upscope $end
   $scope module sign_ext $end
    $var wire 32 4 imm_ext [31:0] $end
    $var wire  2 . imm_src [1:0] $end
    $var wire 32 & instruction [31:0] $end
   $upscope $end
  $upscope $end
 $upscope $end
$enddefinitions $end


#0
b00000000000000000000000100000000 #
b00000000000000000000000000000000 $
b00000000000000000000000000000100 %
b00000000000000000000000010010011 &
1'
1(
0)
0*
0+
0,
b00 -
b00 .
b00000000000000000000000000000000 /
b00000000000000000000000000000000 0
b00000000000000000000000000000000 1
12
b0010 3
b00000000000000000000000000000000 4
b00000000000000000000000000000000 5
06
b00000000000000000000000000000100 7
b00000000000000000000000000000000 8
b0010011 9
b00000 :
b00000 ;
b00001 <
b00000000000000000000000000000000 =
b00000000000000000000000000000000 >
b00000000000000000000000000000000 ?
b00000000000000000000000000000000 @
b00000000000000000000000000000000 A
b00000000000000000000000000000000 B
b00000000000000000000000000000000 C
b00000000000000000000000000000000 D
b00000000000000000000000000000000 E
b00000000000000000000000000000000 F
b00000000000000000000000000000000 G
b00000000000000000000000000000000 H
b00000000000000000000000000000000 I
b00000000000000000000000000000000 J
b00000000000000000000000000000000 K
b00000000000000000000000000000000 L
b00000000000000000000000000000000 M
b00000000000000000000000000000000 N
b00000000000000000000000000000000 O
b00000000000000000000000000000000 P
b00000000000000000000000000000000 Q
b00000000000000000000000000000000 R
b00000000000000000000000000000000 S
b00000000000000000000000000000000 T
b00000000000000000000000000000000 U
b00000000000000000000000000000000 V
b00000000000000000000000000000000 W
b00000000000000000000000000000000 X
b00000000000000000000000000000000 Y
b00000000000000000000000000000000 Z
b00000000000000000000000000000000 [
b00000000000000000000000000000000 \
b00000000000000000000000000000000 ]
1^
1_
b00000000000000000000000000000000 `
b00000000000000000000000000000000 a
#1
0^
#2
b00000000000000000000000000100000 ]
1^
#3
0^
#4
1^
#5
0^
#6
1^
#7
0^
#8
1^
#9
0^
#10
1^
#11
0^
0_
#12
b00000000000000000000000000000100 $
b00000000000000000000000000001000 %
b00000000000100000000000100010011 &
b00000000000000000000000000000001 1
02
b00000000000000000000000000000001 4
b00000000000000000000000000000001 5
b00000000000000000000000000001000 7
b00000000000000000000000000000101 8
b00001 ;
b00010 <
1^
b00000000000000000000000000000001 `
#13
0^
#14
b00000000000000000000000000001000 $
b00000000000000000000000000001100 %
b00000000001000001000000110110011 &
0(
b10 -
b00000000000000000000000000000001 0
b00000000000000000000000000000010 4
b00000000000000000000000000001100 7
b00000000000000000000000000001010 8
b0110011 9
b00001 :
b00010 ;
b00011 <
b00000000000000000000000000000001 ?
1^
#15
0^
#16
b00000000000000000000000000001100 $
b00000000000000000000000000010000 %
b01000000001100010000000010110011 &
b00000000000000000000000000000001 /
b00000000000000000000000000000000 1
12
b0110 3
b00000000000000000000010000000011 4
b00000000000000000000000000010000 7
b00000000000000000000010000001111 8
b00010 :
b00011 ;
b00001 <
b00000000000000000000000000000001 @
1^
b00000000000000000000000000000000 `
#17
0^
#18
b00000000000000000000000000010000 $
b00000000000000000000000000010100 %
b00000000001100010111000010110011 &
b00000000000000000000000000000001 1
02
b0000 3
b00000000000000000000000000000011 4
b00000000000000000000000000010100 7
b00000000000000000000000000010011 8
1^
b00000000000000000000000000000001 `
#19
0^
#20
b00000000000000000000000000010100 $
b00000000000000000000000000011000 %
b00000000001100010110000010110011 &
b0001 3
b00000000000000000000000000011000 7
b00000000000000000000000000010111 8
b00000000000000000000000000000001 >
1^
#21
0^
#22
b00000000000000000000000000011000 $
b00000000000000000000000000011100 %
b00000000001100010100000010110011 &
b00000000000000000000000000000000 1
12
b1000 3
b00000000000000000000000000011100 7
b00000000000000000000000000011011 8
1^
b00000000000000000000000000000000 `
#23
0^
#24
b00000000000000000000000000011100 $
b00000000000000000000000000100000 %
b00000000001100010010000010110011 &
b0111 3
b00000000000000000000000000100000 7
b00000000000000000000000000011111 8
b00000000000000000000000000000000 >
1^
#25
0^
#26
b00000000000000000000000000100000 $
b00000000000000000000000000100100 %
b00000000110000000000000110010011 &
1(
b00 -
b00000000000000000000000000000000 /
b00000000000000000000000000000000 0
b00000000000000000000000000001100 1
02
b0010 3
b00000000000000000000000000001100 4
b00000000000000000000000000001100 5
b00000000000000000000000000100100 7
b00000000000000000000000000101100 8
b0010011 9
b00000 :
b01100 ;
b00011 <
1^
b00000000000000000000000000001100 `
#27
0^
#28
b00000000000000000000000000100100 $
b00000000000000000000000000101000 %
b11111111011100011000001000010011 &
b00000000000000000000000000001100 /
b00000000000000000000000000000011 1
b11111111111111111111111111110111 4
b11111111111111111111111111110111 5
b00000000000000000000000000101000 7
b00000000000000000000000000011011 8
b00011 :
b10111 ;
b00100 <
b00000000000000000000000000001100 @
1^
b00000000000000000000000000000011 `
#29
0^
#30
b00000000000000000000000000101000 $
b00000000000000000000000000101100 %
b00000000001000011111001010010011 &
b00000000000000000000000000000001 0
b00000000000000000000000000001110 1
b00000000000000000000000000000010 4
b00000000000000000000000000000010 5
b00000000000000000000000000101100 7
b00000000000000000000000000101010 8
b00010 ;
b00101 <
b00000000000000000000000000000011 A
1^
b00000000000000000000000000001110 `
#31
0^
#32
b00000000000000000000000000101100 $
b00000000000000000000000000110000 %
b00000000001000011110001100010011 &
b00000000000000000000000000110000 7
b00000000000000000000000000101110 8
b00110 <
b00000000000000000000000000001110 B
1^
#33
0^
#34
b00000000000000000000000000110000 $
b00000000000000000000000000110100 %
b00000000001000011100001110010011 &
b00000000000000000000000000110100 7
b00000000000000000000000000110010 8
b00111 <
b00000000000000000000000000001110 C
1^
#35
0^
#36
b00000000000000000000000000110100 $
b00000000000000000000000000111000 %
b00000000001000011010010000010011 &
b00000000000000000000000000111000 7
b00000000000000000000000000110110 8
b01000 <
b00000000000000000000000000001110 D
1^
#37
0^
#38
b00000000000000000000000000111000 $
b00000000000000000000000000111100 %
b00000000000000000010001000100011 &
0'
1+
b01 .
b00000000000000000000000000000000 /
b00000000000000000000000000000000 0
b00000000000000000000000000000100 1
b00000000000000000000000000000100 4
b00000000000000000000000000000100 5
b00000000000000000000000000111100 7
b00000000000000000000000000111100 8
b0100011 9
b00000 :
b00000 ;
b00100 <
b00000000000000000000000000001110 E
1^
b00000000000000000000000000000100 `
#39
0^
#40
b00000000000000000000000000111100 $
b00000000000000000000000001000000 %
b00000000010000000010000010000011 &
1'
1)
1*
0+
b00 .
b00000000000000000000000000000011 0
b00000000000000000000000001000000 7
b00000000000000000000000001000000 8
b0000011 9
b00100 ;
b00001 <
1^
b00000000000000000000000000000000 `
#41
0^
#42
b00000000000000000000000001000000 $
b00000000000000000000000001000100 %
b00000000001000001000010001100011 &
0'
0(
0)
0*
1,
b01 -
b10 .
b00000000000000000000000000000001 0
b11111111111111111111111111111111 1
b0110 3
b00000000000000000000000000001000 4
b00000000000000000000000000000001 5
b00000000000000000000000001000100 7
b00000000000000000000000001001000 8
b1100011 9
b00001 :
b00010 ;
b01000 <
1^
b11111111111111111111111111111111 `
#43
0^
#44
b00000000000000000000000001000100 $
b00000000000000000000000001001100 %
b00000000000000001000010001100011 &
b00000000000000000000000000000000 0
b00000000000000000000000000000000 1
12
b00000000000000000000000000000000 5
16
b00000000000000000000000001001000 7
b00000000000000000000000001001100 8
b00000 ;
1^
b00000000000000000000000000000000 `
#45
0^
#46
b00000000000000000000000001001100 $
b00000000000000000000000001010000 %
b00000000001001001000010010010011 &
1'
1(
0,
b00 -
b00 .
b00000000000000000000000000000001 0
b00000000000000000000000000000010 1
02
b0010 3
b00000000000000000000000000000010 4
b00000000000000000000000000000010 5
06
b00000000000000000000000001010000 7
b00000000000000000000000001001110 8
b0010011 9
b01001 :
b00010 ;
b01001 <
1^
b00000000000000000000000000000010 `
#47
0^
#48
b00000000000000000000000001010000 $
b00000000000000000000000001010100 %
b00000000000000000000000000000010 /
b00000000000000000000000000000100 1
b00000000000000000000000001010100 7
b00000000000000000000000001010010 8
b00000000000000000000000000000010 F
1^
b00000000000000000000000000000100 `
#49
0^
#50
b00000000000000000000000001010100 $
b00000000000000000000000001011000 %
b01000000100101000101001110110011 &
0(
b10 -
b00000000000000000000000000001110 /
b00000000000000000000000000000100 0
b00000000000000000000000000000000 1
12
b1011 3
b00000000000000000000010000001001 4
b00000000000000000000000000000100 5
b00000000000000000000000001011000 7
b00000000000000000000010001011101 8
b0110011 9
b01000 :
b01001 ;
b00111 <
b00000000000000000000000000000100 F
1^
b00000000000000000000000000000000 `
#51
0^
#52
b00000000000000000000000001011000 $
b00000000000000000000000001011100 %
b00000000000000000000000000000000 &
0'
b00 -
b00000000000000000000000000000000 /
b00000000000000000000000000000000 0
b0010 3
b00000000000000000000000000000000 4
b00000000000000000000000000000000 5
b00000000000000000000000001011100 7
b00000000000000000000000001011000 8
b0000000 9
b00000 :
b00000 ;
b00000 <
b00000000000000000000000000000000 D
1^
#53
0^
#54
b00000000000000000000000001011100 $
b00000000000000000000000001100000 %
b00000000000000000000000001100000 7
b00000000000000000000000001011100 8
1^
#55
0^
#56
b00000000000000000000000001100000 $
b00000000000000000000000001100100 %
b00000000000000000000000001100100 7
b00000000000000000000000001100000 8
1^
#57
0^
#58
b00000000000000000000000001100100 $
b00000000000000000000000001101000 %
b00000000000000000000000001101000 7
b00000000000000000000000001100100 8
1^
#59
0^
#60
b00000000000000000000000001101000 $
b00000000000000000000000001101100 %
b00000000000000000000000001101100 7
b00000000000000000000000001101000 8
1^
#61
0^
#62
b00000000000000000000000001101100 $
b00000000000000000000000001110000 %
b00000000000000000000000001110000 7
b00000000000000000000000001101100 8
1^
#63
0^
#64
b00000000000000000000000001110000 $
b00000000000000000000000001110100 %
b00000000000000000000000001110100 7
b00000000000000000000000001110000 8
1^
#65
0^
#66
b00000000000000000000000001110100 $
b00000000000000000000000001111000 %
b00000000000000000000000001111000 7
b00000000000000000000000001110100 8
1^
#67
0^
#68
b00000000000000000000000001111000 $
b00000000000000000000000001111100 %
b00000000000000000000000001111100 7
b00000000000000000000000001111000 8
1^
#69
0^
#70
b00000000000000000000000001111100 $
b00000000000000000000000010000000 %
b00000000000000000000000010000000 7
b00000000000000000000000001111100 8
1^
#71
0^
#72
b00000000000000000000000010000000 $
b00000000000000000000000010000100 %
b00000000000000000000000010000100 7
b00000000000000000000000010000000 8
1^
#73
0^
#74
b00000000000000000000000010000100 $
b00000000000000000000000010001000 %
b00000000000000000000000010001000 7
b00000000000000000000000010000100 8
1^
#75
0^
#76
b00000000000000000000000010001000 $
b00000000000000000000000010001100 %
b00000000000000000000000010001100 7
b00000000000000000000000010001000 8
1^
#77
0^
#78
b00000000000000000000000010001100 $
b00000000000000000000000010010000 %
b00000000000000000000000010010000 7
b00000000000000000000000010001100 8
1^
#79
0^
#80
b00000000000000000000000010010000 $
b00000000000000000000000010010100 %
b00000000000000000000000010010100 7
b00000000000000000000000010010000 8
1^
#81
0^
#82
b00000000000000000000000010010100 $
b00000000000000000000000010011000 %
b00000000000000000000000010011000 7
b00000000000000000000000010010100 8
1^
#83
0^
#84
b00000000000000000000000010011000 $
b00000000000000000000000010011100 %
b00000000000000000000000010011100 7
b00000000000000000000000010011000 8
1^
#85
0^
#86
b00000000000000000000000010011100 $
b00000000000000000000000010100000 %
b00000000000000000000000010100000 7
b00000000000000000000000010011100 8
1^
#87
0^
#88
b00000000000000000000000010100000 $
b00000000000000000000000010100100 %
b00000000000000000000000010100100 7
b00000000000000000000000010100000 8
1^
#89
0^
#90
b00000000000000000000000010100100 $
b00000000000000000000000010101000 %
b00000000000000000000000010101000 7
b00000000000000000000000010100100 8
1^
#91
0^
#92
b00000000000000000000000010101000 $
b00000000000000000000000010101100 %
b00000000000000000000000010101100 7
b00000000000000000000000010101000 8
1^
#93
0^
#94
b00000000000000000000000010101100 $
b00000000000000000000000010110000 %
b00000000000000000000000010110000 7
b00000000000000000000000010101100 8
1^
#95
0^
#96
b00000000000000000000000010110000 $
b00000000000000000000000010110100 %
b00000000000000000000000010110100 7
b00000000000000000000000010110000 8
1^
#97
0^
#98
b00000000000000000000000010110100 $
b00000000000000000000000010111000 %
b00000000000000000000000010111000 7
b00000000000000000000000010110100 8
1^
